{
  "project_info": {
    "project_number": "688319085109",
    "project_id": "iut-astrolabe",
    "storage_bucket": "iut-astrolabe.appspot.com"
  },
  "client": [
    {
      "client_info": {
        "mobilesdk_app_id": "1:688319085109:android:4c5603a1fcf570ea8c8f7c",
        "android_client_info": {
          "package_name": "com.example.astrolabe_user"
        }
      },
      "oauth_client": [],
      "api_key": [
        {
          "current_key": "AIzaSyDdf-Ef-PVcP0YtY5elC6pVPS3m1hbXUr0"
        }
      ],
      "services": {
        "appinvite_service": {
          "other_platform_oauth_client": []
        }
      }
    }
  ],
  "configuration_version": "1"
}